LICENSE
README.md
setup.cfg
setup.py
hatebase/__init__.py
hatebase.egg-info/PKG-INFO
hatebase.egg-info/SOURCES.txt
hatebase.egg-info/dependency_links.txt
hatebase.egg-info/requires.txt
hatebase.egg-info/top_level.txt
hatebase/tests/__init__.py
hatebase/tests/test.py