Metadata-Version: 2.1
Name: hatebase
Version: 1.0.3
Summary: Python Version of Andrew Welter's Hatebase Wrapper, based on DanielJDufour's implementation
Home-page: https://github.com/DanielJDufour/hatebase
Author: Daniel J. Dufour & Alexander Meier
Author-email: daniel.j.dufour@gmail.com
License: UNKNOWN
Download-URL: https://github.com/DanielJDufour/hatebase/tarball/download
Keywords: conflict,hatespeech,language,nlp,python,tagging
Platform: UNKNOWN
License-File: LICENSE
